odoo/addons/shopinvader_customer_price_wishlist/README.rst
odoo/addons/shopinvader_customer_price_wishlist/__init__.py
odoo/addons/shopinvader_customer_price_wishlist/__manifest__.py
odoo/addons/shopinvader_customer_price_wishlist/i18n/shopinvader_customer_price_wishlist.pot
odoo/addons/shopinvader_customer_price_wishlist/readme/CONTRIBUTORS.rst
odoo/addons/shopinvader_customer_price_wishlist/readme/CREDITS.rst
odoo/addons/shopinvader_customer_price_wishlist/readme/DESCRIPTION.rst
odoo/addons/shopinvader_customer_price_wishlist/services/__init__.py
odoo/addons/shopinvader_customer_price_wishlist/services/wishlist.py
odoo/addons/shopinvader_customer_price_wishlist/static/description/index.html
odoo/addons/shopinvader_customer_price_wishlist/tests/__init__.py
odoo/addons/shopinvader_customer_price_wishlist/tests/test_wishlist_price.py
odoo13_addon_shopinvader_customer_price_wishlist-13.0.1.1.0.dist-info/METADATA
odoo13_addon_shopinvader_customer_price_wishlist-13.0.1.1.0.dist-info/WHEEL
odoo13_addon_shopinvader_customer_price_wishlist-13.0.1.1.0.dist-info/top_level.txt
odoo13_addon_shopinvader_customer_price_wishlist-13.0.1.1.0.dist-info/RECORD
